Metadata-Version: 1.2
Name: tilemapbase
Version: 0.4.5
Summary: Use OpenStreetMap tiles as basemaps in python / matplotlib
Home-page: https://github.com/MatthewDaws/TileMapBase
Author: Matt Daws
Author-email: matthew.daws@gmail.com
License: MIT
Keywords: basemap,OpenStreetMap,tiles
Platform: UNKNOWN
Classifier: Development Status :: 5 - Production/Stable
Classifier: License :: OSI Approved :: MIT License
Classifier: Programming Language :: Python :: 3 :: Only
Classifier: Topic :: Scientific/Engineering :: GIS
Requires-Python: >=3.5
